paravery/__init__.py
paravery/multiplicando.py
paravery-0.0.4.dist-info/LICENSE
paravery-0.0.4.dist-info/METADATA
paravery-0.0.4.dist-info/WHEEL
paravery-0.0.4.dist-info/top_level.txt
paravery-0.0.4.dist-info/RECORD
