Metadata-Version: 2.1
Name: paravery
Version: 0.0.4
Summary: Meu primeiro pacote em python
Author: Luis Eduardo
Author-email: duardos36@gmail.com
License-File: LICENSE
